pxi4jss/__init__.py
pxi4jss/main.py
pxi4jss/solver.py
pxi4jss/utils/__init__.py
pxi4jss/utils/simulator.py
tests/__init__.py
tests/test_main.py
pxi4jss-1.0.dist-info/LICENCE
pxi4jss-1.0.dist-info/METADATA
pxi4jss-1.0.dist-info/WHEEL
pxi4jss-1.0.dist-info/top_level.txt
pxi4jss-1.0.dist-info/RECORD
