Metadata-Version: 2.1
Name: pxi4jss
Version: 1.0
Summary: It is modeling tool for automatically generating Ising models from JSS Petri nets.
Home-page: https://github.com/kanekou/pxi4jss
Author: kanekou
Author-email: k208580@ie.u-ryukyu.ac.jp
License: MIT
Classifier: Programming Language :: Python :: 3.7
Classifier: License :: OSI Approved :: MIT License
License-File: LICENCE
Requires-Dist: snakes-utils (>=2.0.2)
Requires-Dist: dwave-neal
Requires-Dist: pandas
Requires-Dist: pyqubo
